CHANGES.rst
DESCRIPTION.rst
LICENSE
MANIFEST.in
README.md
setup.py
src/ldc_google/__init__.py
src/ldc_google/class_lister.py
src/ldc_google.egg-info/PKG-INFO
src/ldc_google.egg-info/SOURCES.txt
src/ldc_google.egg-info/dependency_links.txt
src/ldc_google.egg-info/entry_points.txt
src/ldc_google.egg-info/requires.txt
src/ldc_google.egg-info/top_level.txt
src/ldc_google/filter/__init__.py
src/ldc_google/filter/_google_translate.py